{"schema":{"hostname":{"id":"hostname","type":{"dataType":"string"},"label":"hostname"},"region":{"id":"region","type":{"dataType":"string"},"label":"region","constraints":{"required":false}},"workload":{"id":"workload","type":{"dataType":"string"},"label":"workload","constraints":{"required":false}},"datacenter":{"id":"datacenter","type":{"dataType":"string"},"label":"datacenter","constraints":{"required":false}}},"layout":{"pages":[{"id":"page_rzr3ja02","title":"General","sections":[{"id":"section_lfhon0uh","fields":[{"id":"hostname","display":"textField","signpostPosition":"right-middle","state":{"visible":true,"read-only":false}}]},{"id":"section_e072l5zs","fields":[{"id":"region","display":"textField","signpostPosition":"right-middle","state":{"visible":true,"read-only":false}}]},{"id":"section_xnfhvg3y","fields":[{"id":"workload","display":"textField","signpostPosition":"right-middle","state":{"visible":true,"read-only":false}}]},{"id":"section_utqnqr00","fields":[{"id":"datacenter","display":"textField","signpostPosition":"right-middle","state":{"visible":true,"read-only":false}}]}]}]},"itemId":""}